coffeeAPI/__init__.py
coffeeAPI/demo.py
coffeeAPI/gaoapi.py
coffeeAPI/whfunc.py
coffeeAPI/下单.py
coffeeAPI/查询账户保证金比例.py
coffeeAPI/查询账户手续费比例.py
coffeeAPI/综合测试代码.py
coffeeAPI/获取行情k线序列.py
coffeeAPI/获取行情quote切片.py
coffeeAPI/获取行情tick序列.py
coffeeAPI/获取账户成交记录.py
coffeeAPI/获取账户持仓.py
coffeeAPI/获取账户订单.py
coffeeAPI/获取账户资金.py
coffeeAPI-0.1.1.dist-info/METADATA
coffeeAPI-0.1.1.dist-info/WHEEL
coffeeAPI-0.1.1.dist-info/top_level.txt
coffeeAPI-0.1.1.dist-info/RECORD
