Metadata-Version: 2.1
Name: coffeeAPI
Version: 0.1.1
Summary: coffeetrader的python量化交易库
Home-page: 
Author: coffeetrader
Author-email: 
Classifier: Programming Language :: Python :: 3.7
Classifier: License :: OSI Approved :: MIT License
Classifier: Operating System :: OS Independent
Classifier: Topic :: Office/Business :: Financial :: Investment
Requires-Python: >=3.7
Requires-Dist: aiohttp ==3.8.6
Requires-Dist: aioredis ==2.0.1
Requires-Dist: aiosignal ==1.3.1
Requires-Dist: async-timeout ==4.0.3
Requires-Dist: asynctest ==0.13.0
Requires-Dist: attrs ==24.2.0
Requires-Dist: certifi ==2025.4.26
Requires-Dist: charset-normalizer ==3.4.2
Requires-Dist: click ==8.1.8
Requires-Dist: colorama ==0.4.6
Requires-Dist: filelock ==3.12.2
Requires-Dist: frozenlist ==1.3.3
Requires-Dist: graphql-core ==3.2.6
Requires-Dist: idna ==3.10
Requires-Dist: importlib-metadata ==6.7.0
Requires-Dist: janus ==1.0.0
Requires-Dist: llvmlite ==0.39.1
Requires-Dist: multidict ==6.0.5
Requires-Dist: numba ==0.56.4
Requires-Dist: numpy ==1.21.6
Requires-Dist: packaging ==24.0
Requires-Dist: pandas ==1.3.5
Requires-Dist: psutil ==7.0.0
Requires-Dist: PyJWT ==2.8.0
Requires-Dist: PyQt5 ==5.15.2
Requires-Dist: pyqt5-plugins ==5.15.2.2.2
Requires-Dist: PyQt5-Qt5 ==5.15.2
Requires-Dist: PyQt5-sip ==12.12.2
Requires-Dist: pyqt5-tools ==5.15.2.3
Requires-Dist: python-dateutil ==2.9.0.post0
Requires-Dist: python-dotenv ==0.21.1
Requires-Dist: pytz ==2025.2
Requires-Dist: qt5-applications ==5.15.2.2.3
Requires-Dist: qt5-tools ==5.15.2.1.3
Requires-Dist: redis ==5.0.8
Requires-Dist: requests ==2.31.0
Requires-Dist: schedule ==1.2.2
Requires-Dist: scipy ==1.7.3
Requires-Dist: sgqlc ==16.3
Requires-Dist: shinny-structlog ==0.0.4
Requires-Dist: simplejson ==3.20.1
Requires-Dist: six ==1.17.0
Requires-Dist: tqsdk ==3.8.1
Requires-Dist: tqsdk-ctpse ==1.0.2
Requires-Dist: tqsdk-sm ==1.0.5
Requires-Dist: typing-extensions ==4.7.1
Requires-Dist: urllib3 ==1.26.9
Requires-Dist: websockets ==11.0.3
Requires-Dist: yarl ==1.9.4
Requires-Dist: zipp ==3.15.0
